CHANGES.rst
MANIFEST.in
README.rst
setup.py
docs/Makefile
docs/source/conf.py
docs/source/config.rst
docs/source/index.rst
docs/source/msg_layout.rst
docs/source/api/cef_plugin.rst
heka_cef/__init__.py
heka_cef/cef_plugin.py
heka_cef/tests/__init__.py
heka_cef/tests/ceftests.py
heka_cef/tests/test_cef.py
heka_py_cef.egg-info/PKG-INFO
heka_py_cef.egg-info/SOURCES.txt
heka_py_cef.egg-info/dependency_links.txt
heka_py_cef.egg-info/not-zip-safe
heka_py_cef.egg-info/requires.txt
heka_py_cef.egg-info/top_level.txt