Metadata-Version: 1.1
Name: heka-py-cef
Version: 0.3.1
Summary: CEF extensions to metrics logging
Home-page: https://github.com/mozilla-services/heka-cef
Author: Victor Ng
Author-email: vng@mozilla.com
License: MPLv2.0
Keywords: heka metrics logging client cef
Platform: UNKNOWN
Classifier: License :: OSI Approved :: Mozilla Public License 2.0 (MPL 2.0)
